LICENSE
MANIFEST.in
README.md
README.rst
setup.cfg
setup.py
django_iamport.egg-info/PKG-INFO
django_iamport.egg-info/SOURCES.txt
django_iamport.egg-info/dependency_links.txt
django_iamport.egg-info/requires.txt
django_iamport.egg-info/top_level.txt
payment/__init__.py
payment/admin.py
payment/apps.py
payment/forms.py
payment/iamport_rest.py
payment/models.py
payment/tests.py
payment/urls.py
payment/views.py
payment/migrations/__init__.py
payment/templates/payment/payment_base.html
payment/templates/payment/result.html
payment/templates/payment/summary.html