Metadata-Version: 1.1
Name: django-iamport
Version: 0.2.0
Summary: Iamport implementation for Django 2+
Home-page: https://github.com/bluedisk/django-iamport
Author: Wonwoo, lee
Author-email: bluedisk@gmail.com
License: MIT
Keywords: django iamport korean-pg payment
Platform: UNKNOWN
Classifier: Development Status :: 4 - Beta
Classifier: Intended Audience :: Developers
Classifier: Framework :: Django :: 2.0
Classifier: License :: OSI Approved :: MIT License
Classifier: Programming Language :: Python :: 3 :: Only
Classifier: Programming Language :: Python :: 3.6
Classifier: Programming Language :: Python :: 3.7
